{
  "decision_id": "Гж_3905_13",
  "decision_number": "Гж 3905/13",
  "court": "Apelacioni sud u Beogradu",
  "decision_date": "2015-03-05",
  "matter": "gradjanska",
  "heading": "",
  "raw_text": "СУПАРНИЧАРСТВОИТРОШКОВИПОСТУПКАУ процесној заједници обичних супарничара право на \nнакнаду трошкова цени се\n према успеху сваког од супарничара \nпонаособ. \nИз бразложења: \nНеосновано се жалбом тужилаца оспорава одлука о трошковима поступка , указивањем да је у овој парници пуномоћ -\nник из реда адвоката заступао две странке и да му применом Тарифе о наградама и накнадама трошкова за рад адвоката (\" Сл. \nгласник РС\" 121/12) по овом основу за сваку радњу коју преду -\nзима припада награда увећана за 50% због заступања тужиоца \nА.Г. и тужиље Ж.Г.. Апелаци oни суд налази да у конкретном \nслучају нема места преиначењу одлуке о трошковима . Наиме , \nтужиоци у овој парници нису јединствени нити нужни супарни -\nчари и нису у истој мери успели у овом спору . Тужиоци су \nобични супарничари , који по чл. 209. ЗПП представљају самосталне странке у поступку , те радње или пропуштања једног од \nсупарничара не користе нити штете другом супарничару . То \nподразумева да свако од тужилаца , који се у овој парници налазе у процесној заједници као супарничари из чл. 209. ЗПП-а, може тражити и остварити правну заштиту у посебној парници , \nнезависно од другог супарничара . Стога се и њихово право на \nнакнаду трошкова мора ценити према критеријумима за досуђи -\nвање трошкова за сваког од тужилаца понаособ . Наиме , право \nна накнаду трошкова у парничном поступку припада странкама\n\nАпелациони суд у Београду \n \n \n \n136 \n \nу складу са критеријумом успеха у спору ( члан 153. ЗПП), кривице у проузроковању ( члан 155. ЗПП) и опредељеног захтева \n(члан 163. ЗПП). Структура и висина трошкова зависе од тога да \nли су били потребни за вођење парнице , о чему одлучује суд ценећи све околности конкретног случаја ( члан 154. ЗПП). У парницама ради накнаде нематеријалне штете висина трошкова на \nиме награде за рад адвоката и на име таксе се одмерава према \nдосуђеном износу накнаде , с тим што, независно од висине досуђене накнаде , страна која је успела у парници за накнаду неимовинске штете има право на накнаду трошкова вештачења у \nпуном износу . Накнада трошкова тужиоцу А.Г. у првостепеном \nпоступку по његовом захтеву за накнаду нематеријалне штете \nје, по оцени Апелационог суда, одмерена правилном применом \nТарифе о наградама и накнадама трошкова за рад адвоката и \nТаксене тарифе , важећим у време првостепеног пресуђења . Делимично преиначење првостепене одлуке није од утицаја на одлуку о трошковима првостепеног поступка , јер би и према висини укупно досуђене накнаде тужиоцу А.Г. припадала накнада \nтрошкова за заступање од стране адвоката у истим износима ко-\nји су досуђени пресудом П.1052/12 од 26.03.2013. године . Међутим, износ трошкова у поступку по захтеву тужиље Ж.Г. за накнаду материјалне штете , цени се према критеријуму постигну -\nтог успеха у спору , па у ситуацији када странка делимично успе \nу парници има места примени одредбе 153. став 2. ЗПП-а, којом \nје предвиђена могућност да свака странка сноси своје трошкове \nпоступка . Имајући у виду висину првобитно постављеног тужбеног захтева за накнаду материјалне штете од 5.490,00 динара и висину досуђеног износа од 2.500,00 динара , успех тужилачке и тужене стране је, и по налажењу другостепеног суда, \nподједнак . Да је о захтеву тужиље Ж.Г. за накнаду материјалне \nштете расправљано у посебној парници , правилна одлука о трошковима би гласила да свака странка сноси своје трошкове поступка . Код чињенице да тужиљи Ж.Г. у смислу чл. 153. став 2. \nЗПП трошкови не би били досуђени у посебној парници , нема \nместа ни увећању досуђеног износа трошкова за 50% по основу \nзаступања ове тужиље као супарничара у овом поступку . Стога\n\nБилтен број 7/2015 \n \n \n \n137\nје жалба у наведеном делу одбијена као неоснована и решење о \nтрошковима поступка садржано у ставу четвртом изреке првостепене пресуде је применом члана 401. став 1. тачка 2. потвр -\nђено. \n(Пресуда Апелационог суда у Београду Гж 3905/13 од 05. \nмарта 2015. године)",
  "source": "AS Beograd Bilten 7 (2015)",
  "source_url": "https://bg.ap.sud.rs/files/Bilten%20broj%207%20u%20elektronskoj%20formi.pdf#page=90",
  "scraped_at": "2026-05-31T10:08:26.113172+00:00",
  "bilten_source": true
}