{
  "decision_id": "бр_8_12",
  "decision_number": "бр. 8/12",
  "court": "Apelacioni sud u Beogradu",
  "decision_date": "2012-01-26",
  "matter": "gradjanska",
  "heading": "ГРАЂАНСКООДЕЉЕЊЕ",
  "raw_text": "Билтен број 4/2012 \n \n \n \n119\nовим споровима физичко лице, ако је са странком у односу матери-\nјалног супарничарства. \nУ одредби чл. 25. ст. 1. тачка 1. Закона о уређењу судова јасно \nје разграничена стварна надлежност између основних и привредних \nсудова. Законодавац је парничне странке сврстао у две групе, у првој су привредни субјекти у коју спадају и предузетници, а у другој \nсу остала правна лица. За спорове између привредних субјеката \nувек је стварно надлежан привредни суд без обзира на предмет спора. У споровима у којима је једна странка привредни субјект, а друга друго правно лице, привредни суд је стварно надлежан за суђење \nсамо у спору који је настао у обављању делатности привредног субјекта. Стварна надлежност привредног суда у овим споровима се \nутврђује на основу субјективно – објективног критеријума који је \nбио прописан и у чл. 15. ст. 1. тачка а раније важећег Закона о судовима, одредницом међусобни привредни односи. \nОвакав став изражен је у закључку Грађанског одељења Врховног касационог суда од 04.10.2010. године, који у међувремену \nније измењен. \nУ спору по тужби привредног субјекта против другог правног \nлица, Републике Србије, ради накнаде штете због незаконитог рада \nдржавног органа спор је грађанскоправне природе јер је настао у вези са вршењем јавне власти тужене, будући да је тужбени захтев заснован на тврдњи да надлежни орган тужене није поштовао законом \nпрописану процедуру и материјалноправна овлашћења приликом \nвршења јавне власти, чиме је тужиоцу проузрокована штета. Стога \nу овим споровима спор није настао у обављању делатности тужиоца \nкао привредног субјекта, па је за суђење стварно надлежан суд опште надлежности. \n(Закључак са седнице Грађанског одељења Апелационог \nсуда у Београду одржан дана 24. септембра 2012. године)\n\nАпелациони суд у Београду \n \n \n \n120 \n \n \nГРАЂАНСКООДЕЉЕЊЕ \n \nПарнични поступак \n \n \nСУКОБНАДЛЕЖНОСТИВиши суд се не може огласити стварно ненадлежним у \nпарници у којој је прихватио стварну надлежност од основног \nсуда и наставио са извођењем доказа, без обзира што тужилац \nкасније определи вредност предмета спора из надлежности \nосновног суда. \nИз образложења: \n\"Према стању у списима утврђено је да је тужиља у тужби навела предност предмета спора, а Виши суд у Београду није, након \nшто се Први основни суд у Београду огласио ненадлежним и доставио списе, изазвао сукоб надлежности, већ је заказивао рочишта за \nглавну расправу и изводио доказе, из чега произлази да је прихватио своју надлежност у овој правној ствари. Зато се сада, у овој фази поступка, Виши суд није могао огласити ненадлежним, без обзира што је тужиља определила вредност спора на 35.000 евра у динарској противвредности. Из свега наведеног произлази да приликом поступања у овом парничном поступку није проверена тачност \nвредности предмета спора, на начин прописан одредбом члана 34. \nстав 3. Закона о парничном поступку, па Виши суд у Београду, у \nфази главне расправе у којој се налазио предметни спор, није могао \nда утврђује нову вредност предмета спора, нити је тужиља у овој \nфази поступка могла да мења вредност предмета спора, који се односи на предметни стан, па Виши суд у Београду није могао да се у \nтоку трајања главне расправе, када је отпочео поступак извођења \nдоказа, огласи стварно ненадлежним за поступање у овој парници,\n\nБилтен број 4/2012 \n \n \n \n121\nсамо на основу новоозначене вредности предмета спора, у ситуаци-\nји када није изазвао сукоб надлежности након доношења решења \nПрвог основног суда у Београду, којим се исти огласио ненадлежним за поступање у овој правној ствари.\" \n(Решење Апелационог суда у Београду Р. бр. 8/12 од 26. јануара 2012. године)",
  "source": "AS Beograd Bilten 4 (2012)",
  "source_url": "https://bg.ap.sud.rs/files/Bilten-4%202012.pdf#page=69",
  "scraped_at": "2026-05-31T10:07:57.862576+00:00",
  "bilten_source": true
}