{
  "decision_id": "Гж_1_бр_4169_10",
  "decision_number": "Гж.1 бр. 4169/10",
  "court": "Apelacioni sud u Beogradu",
  "decision_date": "2012-05-30",
  "matter": "radni_sporovi",
  "heading": "",
  "raw_text": "ИЗМЕНАУГОВОРЕНИХУСЛОВАРАДА, \nТРАЈНИПРЕМЕШТАЈ ИПРИВРЕМЕНАПОТРЕБАПОСЛА \n Када постоји привремена потреба посла тада послодавац \nне може запосленог преместити на неодређено време на те послове док се за то не стекну услови. \nИз образложења: \nПоред тога правилно првостепени суд закључује да је тужбени захтев тужиље основан и из разлога што тужиља није могла бити \nраспоређена на ново радно место на неодређено време, обзиром да у \nвреме понуде нису наступили измењени услови рада, исти су наступили касније, повећањем броја извршилаца са 1 на 2 која измена је \nизвршена на основу Одлуке Генералног директора тужене заведене \nпод бројем 834 од 10.03.2008. године ( понуда је учињена дана \n07.02.2008. године). То значи да у време понуде и премештаја није \nпостојало слободно радно место пошто је на те послове већ био распоређен један извршилац, колико је било и у то време предвиђено \nизвршилаца на тим пословима. То што је Оливера Савић Ранчић би-\n\nАпелациони суд у Београду \n \n \n \n216 \n \nла на породиљском одсуству то је био разлог за понуду и премешта-\nње извршиоца на одређено време, а не на неодређено време као у \nконкретном случају. Ради тога неосновано тужени то правда чињеницом, а како је то и наведено у самом Анексу, да је било неопходно извршити попуњавање упражњеног радног места због одласка \nзапослене Оливере Ранчић на породиљско одсуство у периоду од \n07.02.2008.- 06.02.2009. године. Међутим, и у ситуацији да је било \nпотребе да се попуни упражњено радно место на коме је био запослен само 1 извршилац, што је неспорно, ради организације посла, \nто је могло бити учињено само распоређивањем тужиље и потписивањем Анекса на одређено време све до измене Правилника, а након \nизмене Правилника и на неодређено време што указује на потребу \nпроцеса рада. Зато је правилан закључак првостепеног суда да учи-\nњена понуда пре донете Одлуке о повећању броја извршилаца и измене Правилника чини овај Анекс о распореду тужиље на неодређено радно време незаконитим. \nПри наведеном без утицаја су наводи из жалбе којима се указује да се измена по овој одлуци врши од 01.01.2008. године, јер у \nтренутку понуде није дошло до повећања броја извршилаца, па самим тим ни до измене уговорених услова рада. Уколико је постојала потреба ради замене одсутног радника у циљу обављања ових \nпослова то је могло бити учињено само распоређивањем тужиље на \nодређено време, а не на неодређено и то ретроактивном изменом \nПравилника. Све ово правилно закључује и првостепени суд. \nСве наведено имајући у виду одредбу члана 171. став 1. Закона о раду којом је прописано да послодавац може запосленом да понуди измену уговорених услова рада ради премештаја на други одговарајући посао, због потреба процеса и организације рада. \n(Пресуда Апелационог суда у Београду Гж.1 бр. 4169/10 од \n30. маја 2012. године)",
  "source": "AS Beograd Bilten 4 (2012)",
  "source_url": "https://bg.ap.sud.rs/files/Bilten-4%202012.pdf#page=210",
  "scraped_at": "2026-05-31T10:07:57.864623+00:00",
  "bilten_source": true
}