{
  "broj": "011-00-00355/2022-06",
  "datum": "22.06.2022",
  "ministarstvo": "Ministarstvo privrede",
  "oblast": "privredna društva",
  "naziv": "Podela dobiti DOO — uslovi za isplatu",
  "tekst": "Pitanje: Pod kojim uslovima DOO može da isplati dobit (dividendu) osnivačima?\n\nOdgovor: Prema članu 180-182 Zakona o privrednim društvima, DOO može doneti odluku o podeli dobiti ako su ispunjeni sledeći uslovi: 1) postoji neraspoređena dobit po godišnjem finansijskom izveštaju; 2) društvo može podmiriti sve obaveze po dospeću; 3) neto imovina nije i neće biti manja od upisanog kapitala plus rezervi. Odluka se donosi prostom većinom glasova skupštine. Neisplaćena dobit se evidentira u bilansu kao obaveza prema osnivačima."
}